youdao.py
youdao_wd-0.1.0.dist-info/DESCRIPTION.rst
youdao_wd-0.1.0.dist-info/METADATA
youdao_wd-0.1.0.dist-info/RECORD
youdao_wd-0.1.0.dist-info/WHEEL
youdao_wd-0.1.0.dist-info/entry_points.txt
youdao_wd-0.1.0.dist-info/metadata.json
youdao_wd-0.1.0.dist-info/top_level.txt
