Metadata-Version: 2.0
Name: youdao-wd
Version: 0.1.0
Summary: Query words meanings via the command line
Home-page: https://github.com/chenjiandongx/youdao-wd
Author: chenjiandongx
Author-email: chenjiandongx@qq.com
License: MIT
Platform: UNKNOWN
